scoss/__init__.py
scoss/cli.py
scoss/html_template.py
scoss/main.py
scoss/my_source.py
scoss/scoss.py
scoss/scoss_client.py
scoss/smoss.py
scoss/metrics/__init__.py
scoss/metrics/metric.py
scoss/metrics/metric_list.py
scoss/metrics/operator_based_metric.py
scoss/metrics/token_based_metric.py
scoss/utils/__init__.py
scoss/utils/parameters.py
scoss/utils/utils.py
tests/__init__.py
tests/my_module.py
tests/test_align_source.py
tests/test_metrics.py
tests/test_rq.py
tests/test_scoss.py
tests/test_smoss.py
tests/test_task_queue.py
scoss-0.0.5.dist-info/LICENSE
scoss-0.0.5.dist-info/METADATA
scoss-0.0.5.dist-info/WHEEL
scoss-0.0.5.dist-info/entry_points.txt
scoss-0.0.5.dist-info/top_level.txt
scoss-0.0.5.dist-info/RECORD
