Metadata-Version: 2.1
Name: scoss
Version: 0.0.5
Summary: A Source Code Similarity System
Home-page: UNKNOWN
Author: Ngoc Bui
Author-email: ngocjr7@gmail.com
License: UNKNOWN
Project-URL: Bug Tracker, https://github.com/ngocjr7/scoss/issues
Project-URL: Documentation, https://github.com/ngocjr7/scoss/blob/master/README.md
Project-URL: Source Code, https://github.com/ngocjr7/scoss
Platform: UNKNOWN
Requires-Python: >=3.6
Requires-Dist: sctokenizer
Requires-Dist: click
Requires-Dist: appdirs
Requires-Dist: jinja2
Requires-Dist: pandas
Requires-Dist: beautifulsoup4
Requires-Dist: requests
